[{"name":"vc.builder.install","duration":688224,"timestamp":1045539543870,"id":"c90939f6-f2a1-466a-a4cb-590b1da8140d","parentId":"01dde1df-e4e2-4f9d-86ca-a8cf6917138b","tags":{"cliType":"npm","lockfileVersion":"3"},"startTime":1774454553545},{"name":"vc.builder.build","duration":20514258,"timestamp":1045540234316,"id":"586e3a91-8188-45a0-8eee-73a42100cf0a","parentId":"01dde1df-e4e2-4f9d-86ca-a8cf6917138b","tags":{"buildScriptName":"build"},"startTime":1774454554236},{"name":"vc.builder","duration":21635487,"timestamp":1045539530216,"id":"01dde1df-e4e2-4f9d-86ca-a8cf6917138b","parentId":"e32312c0-c143-4863-85de-d68460efd308","tags":{"builder.name":"@vercel/next","builder.version":"4.16.3","builder.dynamicallyInstalled":"false","install":"true","build":"true"},"startTime":1774454553532},{"name":"vc.builder.diagnostics","duration":2351,"timestamp":1045561165816,"id":"221df0de-43d5-4e81-b806-a94d51740ed3","parentId":"01dde1df-e4e2-4f9d-86ca-a8cf6917138b","tags":{},"startTime":1774454575167},{"name":"vc.builder.writeBuildResult","duration":25613,"timestamp":1045561168262,"id":"83ce0efb-774e-4222-a9b0-de2e0f314949","parentId":"01dde1df-e4e2-4f9d-86ca-a8cf6917138b","tags":{"buildOutputLength":"1"},"startTime":1774454575170},{"name":"vc.doBuild","duration":21758679,"timestamp":1045539444266,"id":"e32312c0-c143-4863-85de-d68460efd308","parentId":"fd8c9aa2-7c3f-4b49-a605-3d52693db1c0","tags":{},"startTime":1774454553446},{"name":"vc","duration":21768334,"timestamp":1045539434627,"id":"fd8c9aa2-7c3f-4b49-a605-3d52693db1c0","tags":{},"startTime":1774454553436}]